beetsplug/check.py
beets_check-0.15.3.dist-info/METADATA
beets_check-0.15.3.dist-info/WHEEL
beets_check-0.15.3.dist-info/licenses/LICENSE
beets_check-0.15.3.dist-info/RECORD
