Metadata-Version: 2.4
Name: beets-check
Version: 0.15.3
Summary: beets plugin verifying file integrity with checksums
Author-email: Thomas Scholtes <geigerzaehler@axiom.fm>
License-Expression: MIT
License-File: LICENSE
Classifier: Environment :: Console
Classifier: Environment :: Web Environment
Classifier: License :: OSI Approved :: MIT License
Classifier: Programming Language :: Python :: 3
Classifier: Topic :: Multimedia :: Sound/Audio
Classifier: Topic :: Multimedia :: Sound/Audio :: Players :: MP3
Requires-Python: >=3.10
Requires-Dist: beets<3,>=2
Requires-Dist: mediafile>=0.13.0
